pewlib/__init__.py
pewlib/__main__.py
pewlib/calibration.py
pewlib/config.py
pewlib/laser.py
pewlib/io/__init__.py
pewlib/io/agilent.py
pewlib/io/csv.py
pewlib/io/imzml.py
pewlib/io/laser.py
pewlib/io/npz.py
pewlib/io/nu.py
pewlib/io/perkinelmer.py
pewlib/io/textimage.py
pewlib/io/thermo.py
pewlib/io/vtk.py
pewlib/process/__init__.py
pewlib/process/calc.py
pewlib/process/colocal.py
pewlib/process/convolve.py
pewlib/process/filters.py
pewlib/process/peakfinding.py
pewlib/process/register.py
pewlib/process/threshold.py
pewlib/srr/__init__.py
pewlib/srr/config.py
pewlib/srr/srr.py
pewlib-0.10.5.dist-info/licenses/LICENSE
pewlib-0.10.5.dist-info/METADATA
pewlib-0.10.5.dist-info/WHEEL
pewlib-0.10.5.dist-info/entry_points.txt
pewlib-0.10.5.dist-info/top_level.txt
pewlib-0.10.5.dist-info/RECORD
