Metadata-Version: 2.4
Name: pewlib
Version: 0.10.5
Summary: Import, processing and export library for LA-ICP-MS data.
Author-email: Thomas Lockwood <thomas.lockwood@uts.edu.au>
License:                     GNU GENERAL PUBLIC LICENSE
Project-URL: Repository, https://gtihub.com/djdt/pewlib
Project-URL: Documentation, https://djdt.github.io/pewlib
Requires-Python: >=3.9
License-File: LICENSE
Requires-Dist: numpy>=1.22
Provides-Extra: tests
Requires-Dist: pytest; extra == "tests"
Dynamic: license-file
